astar_als-0.0.1.dist-info/METADATA
astar_als-0.0.1.dist-info/RECORD
astar_als-0.0.1.dist-info/WHEEL
astar_als-0.0.1.dist-info/top_level.txt
astar_recommendation/__init__.py
astar_recommendation/collaborative_filtering/__init__.py
astar_recommendation/collaborative_filtering/base.py
astar_recommendation/collaborative_filtering/item_base.py
astar_recommendation/collaborative_filtering/model_base.py
astar_recommendation/collaborative_filtering/user_base.py
